MANIFEST.in
gengo_sync_schedular_data.xml
ir_translation.xml
res_company_view.xml
setup.py
./__init__.py
./__openerp__.py
./ir_translation.py
./res_company.py
./wizard/__init__.py
./wizard/base_gengo_translations.py
i18n/ar.po
i18n/base_gengo.pot
i18n/bs.po
i18n/cs.po
i18n/da.po
i18n/de.po
i18n/es.po
i18n/fr.po
i18n/hr.po
i18n/hu.po
i18n/it.po
i18n/mk.po
i18n/mn.po
i18n/nb.po
i18n/nl.po
i18n/pl.po
i18n/pt.po
i18n/pt_BR.po
i18n/ro.po
i18n/sl.po
i18n/th.po
i18n/tr.po
i18n/zh_CN.po
openerp_base_gengo.egg-info/PKG-INFO
openerp_base_gengo.egg-info/SOURCES.txt
openerp_base_gengo.egg-info/dependency_links.txt
openerp_base_gengo.egg-info/requires.txt
openerp_base_gengo.egg-info/top_level.txt
wizard/base_gengo_translations_view.xml